labedf/__init__.py
labedf/edf_csv.py
labedf/utilities/__init__.py
labedf/utilities/edf.py
labedf-2.0.0.dist-info/LICENSE
labedf-2.0.0.dist-info/METADATA
labedf-2.0.0.dist-info/WHEEL
labedf-2.0.0.dist-info/top_level.txt
labedf-2.0.0.dist-info/RECORD
