Metadata-Version: 2.1
Name: labedf
Version: 2.0.0
Summary: Merge the lab.js csv file and the edf file.
Home-page: https://github.com/s-n-1-0/labedf.py
Download-URL: https://github.com/s-n-1-0/labedf.py
Author: sn-10
License: MIT
Keywords: labjs,lab.js
License-File: LICENSE
Requires-Dist: pyedflib (>=0.1.30)
Requires-Dist: labcsv (>=1.0.4)
Requires-Dist: numpy (>=1.22.4)
